LICENSE
MANIFEST.in
README.md
install.py
setup.cfg
setup.py
rpm_py_installer/__init__.py
rpm_py_installer/version.py
rpm_py_installer.egg-info/PKG-INFO
rpm_py_installer.egg-info/SOURCES.txt
rpm_py_installer.egg-info/dependency_links.txt
rpm_py_installer.egg-info/top_level.txt